bSuite/database/__init__.py
bSuite/database/base.py
bSuite/database/crypto.py
bSuite/database/mapped.py
bSuite/database/models.py
bSuite_database-1.4.0.dist-info/LICENSE
bSuite_database-1.4.0.dist-info/METADATA
bSuite_database-1.4.0.dist-info/WHEEL
bSuite_database-1.4.0.dist-info/top_level.txt
bSuite_database-1.4.0.dist-info/RECORD
