Metadata-Version: 2.1
Name: bSuite-database
Version: 1.4.0
Summary: database submodule of bSuite
Author-email: John Birdwell <j.c.birdwell@gmail.com>
License: GNU GENERAL PUBLIC LICENSE
Requires-Python: >=3.10
License-File: LICENSE
Requires-Dist: psycopg[pool]
Provides-Extra: crypto
Requires-Dist: cryptography ; extra == 'crypto'
